valos/__init__.py
valos-0.0.1.dist-info/METADATA
valos-0.0.1.dist-info/WHEEL
valos-0.0.1.dist-info/top_level.txt
valos-0.0.1.dist-info/RECORD
